pdnsbackup/__init__.py
pdnsbackup/backend.py
pdnsbackup/config.yml
pdnsbackup/export.py
pdnsbackup/parser.py
pdnsbackup-1.0.6.dist-info/licenses/LICENSE
pdnsbackup-1.0.6.dist-info/METADATA
pdnsbackup-1.0.6.dist-info/WHEEL
pdnsbackup-1.0.6.dist-info/entry_points.txt
pdnsbackup-1.0.6.dist-info/top_level.txt
pdnsbackup-1.0.6.dist-info/RECORD
