Metadata-Version: 2.4
Name: pdnsbackup
Version: 1.0.6
Summary: Backup tool for PowerDNS database
Home-page: https://github.com/dmachard/python-pdnsbackup
Author: Denis MACHARD
Author-email: d.machard@gmail.com
Keywords: powerdns pdns database backup
Platform: any
Classifier: License :: OSI Approved :: MIT License
Classifier: Programming Language :: Python :: 3
Classifier: Operating System :: OS Independent
Classifier: Topic :: Software Development :: Libraries
License-File: LICENSE
Requires-Dist: pyyaml
Requires-Dist: aiomysql
Requires-Dist: python-dotenv
Requires-Dist: boto3
Requires-Dist: prometheus-client
Dynamic: author
Dynamic: author-email
Dynamic: classifier
Dynamic: description
Dynamic: description-content-type
Dynamic: home-page
Dynamic: keywords
Dynamic: license-file
Dynamic: platform
Dynamic: requires-dist
Dynamic: summary
